bibolamazi_gui/__init__.py
bibolamazi_gui/bibconfigsynthigh.py
bibolamazi_gui/bibolamazi_gui.py
bibolamazi_gui/favorites.py
bibolamazi_gui/filterinstanceeditor.py
bibolamazi_gui/helpbrowser.py
bibolamazi_gui/openbibfile.py
bibolamazi_gui/overlistbuttonwidget.py
bibolamazi_gui/settingswidget.py
bibolamazi_gui/sourcelisteditor.py
bibolamazi_gui/version.py
bibolamazi_gui/qtauto/__init__.py
bibolamazi_gui/qtauto/bibolamazi_res_rc.py
bibolamazi_gui/qtauto/ui_favoritesoverbtns.py
bibolamazi_gui/qtauto/ui_filterinstanceeditor.py
bibolamazi_gui/qtauto/ui_helpbrowser.py
bibolamazi_gui/qtauto/ui_mainwidget.py
bibolamazi_gui/qtauto/ui_openbibfile.py
bibolamazi_gui/qtauto/ui_overlistbuttonwidget.py
bibolamazi_gui/qtauto/ui_settingswidget.py
bibolamazi_gui/qtauto/ui_sourcelisteditor.py
bibolamazigui-3.2.post1.data/scripts/bibolamazi_gui
bibolamazigui-3.2.post1.dist-info/DESCRIPTION.rst
bibolamazigui-3.2.post1.dist-info/METADATA
bibolamazigui-3.2.post1.dist-info/metadata.json
bibolamazigui-3.2.post1.dist-info/RECORD
bibolamazigui-3.2.post1.dist-info/top_level.txt
bibolamazigui-3.2.post1.dist-info/WHEEL
bibolamazigui-3.2.post1.dist-info/zip-safe
